{
  "header": {
    "description": "Karaoke Mugen Tag File",
    "version": 1
  },
  "tag": {
    "external_database_ids": {
      "anilist": 21787,
      "kitsu": 13115,
      "myanimelist": 33184
    },
    "i18n": {
      "eng": "Battle Girl High School",
      "jpn": "バトルガール ハイスクール",
      "qro": "Battle Girl High School",
      "fre": "Battle Girl High School",
      "chi": "战斗女子高校"
    },
    "name": "Battle Girl High School",
    "repository": "kara.moe",
    "tid": "71489f15-a807-45f6-9c07-25f52531bf67",
    "types": [
      "1",
      "series"
    ]
  }
}