{
  "header": {
    "description": "Karaoke Mugen Tag File",
    "version": 1
  },
  "tag": {
    "aliases": [
      "8",
      "Season 8",
      "heroaca",
      "MHA 8",
      "BNHA 8",
      "ヒロアカ"
    ],
    "external_database_ids": {
      "anilist": 182896,
      "kitsu": 49279,
      "myanimelist": 60098
    },
    "i18n": {
      "eng": "My Hero Academia Final Season",
      "qro": "Boku no Hero Academia FINAL SEASON",
      "jpn": "僕のヒーローアカデミア FINAL SEASON",
      "fre": "My Hero Academia Final Season",
      "rus": "Моя геройская академия 8",
      "tha": "มายฮีโร่ อคาเดเมีย ไฟนอลซีซัน"
    },
    "name": "Boku no Hero Academia FINAL SEASON",
    "repository": "kara.moe",
    "tid": "e465021b-2b07-46ac-ac1a-284971fb759e",
    "types": [
      "1",
      "series"
    ]
  }
}