{
  "header": {
    "description": "Karaoke Mugen Tag File",
    "version": 1
  },
  "tag": {
    "aliases": [
      "Gekijouban"
    ],
    "external_database_ids": {
      "anilist": 172393,
      "myanimelist": 57622
    },
    "i18n": {
      "jpn": "劇場版 うたの☆プリンスさまっ♪ TABOO NIGHT XXXX",
      "qro": "Gekijôban Uta no☆Prince-sama♪: Taboo Night XXXX",
      "chi": "剧场版 歌之☆王子殿下♪ TABOO NIGHT XXXX"
    },
    "name": "Gekijôban Uta no☆Prince-sama♪: Taboo Night XXXX",
    "repository": "kara.moe",
    "tid": "f2f7e646-6bef-4b6f-a14a-bb5ac1dc1990",
    "types": [
      1
    ]
  }
}